autonmt/__init__.py
autonmt/artifact.py
autonmt/common.py
autonmt/configs.py
autonmt/corpus.py
autonmt/main.py
autonmt/pipeline.py
autonmt/pipeline_cache.py
autonmt/steps.py
autonmt/util.py
autonmt/stages/__init__.py
autonmt/stages/build_vocab.py
autonmt/stages/data_query.py
autonmt/stages/merge.py
autonmt/stages/script.py
autonmt/stages/split.py
autonmt/stages/stage.py
autonmt/stages/train.py
AutONMT_tf-0.1.2.dist-info/LICENSE
AutONMT_tf-0.1.2.dist-info/METADATA
AutONMT_tf-0.1.2.dist-info/WHEEL
AutONMT_tf-0.1.2.dist-info/entry_points.txt
AutONMT_tf-0.1.2.dist-info/top_level.txt
AutONMT_tf-0.1.2.dist-info/RECORD
