Metadata-Version: 2.1
Name: AutONMT-tf
Version: 0.1.2
Summary: A configuration tool designed to simplify the creation of complete OpenNMT-tf pipelines
Home-page: https://github.com/mehdidou99/AutONMT-tf
Author: AutONMT
Author-email: mehdibenharrats@yahoo.fr
License: UNKNOWN
Project-URL: Bug Tracker, https://github.com/mehdidou99/AutONMT-tf/issues
Platform: UNKNOWN
Classifier: Development Status :: 3 - Alpha
Classifier: Intended Audience :: Developers
Classifier: Intended Audience :: Science/Research
Classifier: License :: OSI Approved :: MIT License
Classifier: Programming Language :: Python :: 3
Classifier: Programming Language :: Python :: 3 :: Only
Classifier: Programming Language :: Python :: 3.7
Classifier: Programming Language :: Python :: 3.8
Classifier: Programming Language :: Python :: 3.9
Classifier: Topic :: Scientific/Engineering :: Artificial Intelligence
Requires-Python: >=3.7
License-File: LICENSE
Requires-Dist: PyYAML
